reytool/__init__.py
reytool/rall.py
reytool/rcomm.py
reytool/rdata.py
reytool/remail.py
reytool/rexception.py
reytool/rimage.py
reytool/rlog.py
reytool/rmonkey.py
reytool/rmultitask.py
reytool/rnumber.py
reytool/ros.py
reytool/rrandom.py
reytool/rregex.py
reytool/rschedule.py
reytool/rstdout.py
reytool/rsystem.py
reytool/rtable.py
reytool/rtext.py
reytool/rtime.py
reytool/rtype.py
reytool/rwrap.py
reytool/rzip.py
reytool/rdll/__init__.py
reytool/rdll/rdll_inject.py
reytool/rdll/rdll_inject_core.py
reytool-0.436.dist-info/METADATA
reytool-0.436.dist-info/WHEEL
reytool-0.436.dist-info/top_level.txt
reytool-0.436.dist-info/RECORD
