Metadata-Version: 2.4
Name: reytool
Version: 0.436
Summary: Rey's tool method set.
Home-page: https://github.com/reyxbo/reytool/
Author: Rey
Author-email: reyxbo@163.com
Requires-Dist: aiohttp
Requires-Dist: captcha
Requires-Dist: concurrent-log-handler
Requires-Dist: filetype
Requires-Dist: pandas
Requires-Dist: pyzbar
Requires-Dist: qrcode
Requires-Dist: requests
Requires-Dist: apscheduler
Requires-Dist: tqdm
Requires-Dist: urwid
Requires-Dist: varname
Requires-Dist: pdfplumber
Requires-Dist: Pillow
Requires-Dist: psutil
Requires-Dist: pymem
Requires-Dist: python-docx
Dynamic: author
Dynamic: author-email
Dynamic: home-page
Dynamic: requires-dist
Dynamic: summary
